pyautowire/__init__.py
pyautowire/autowire.py
pyautowire/cache.py
pyautowire/error.py
pyautowire/injectable.py
pyautowire-0.3.1.dist-info/LICENSE.txt
pyautowire-0.3.1.dist-info/METADATA
pyautowire-0.3.1.dist-info/WHEEL
pyautowire-0.3.1.dist-info/RECORD
