Metadata-Version: 2.1
Name: pyautowire
Version: 0.3.1
Summary: Good enough autowiring for Python
Home-page: https://github.com/twaslowski/py-autowire
License: gpl3
Keywords: dependency injection,autowire,fixture
Author: Tobias Waslowski
Author-email: tobias.waslowski@gmail.com
Requires-Python: >=3.7,<4.0
Classifier: License :: OSI Approved :: GNU General Public License v3 (GPLv3)
Classifier: License :: Other/Proprietary License
Classifier: Programming Language :: Python :: 3
Classifier: Programming Language :: Python :: 3.7
Classifier: Programming Language :: Python :: 3.8
Classifier: Programming Language :: Python :: 3.9
Classifier: Programming Language :: Python :: 3.10
Classifier: Programming Language :: Python :: 3.11
Classifier: Programming Language :: Python :: 3.12
Classifier: Topic :: Software Development :: Libraries
Classifier: Topic :: Software Development :: Libraries :: Python Modules
Requires-Dist: kink (>=0.7.0,<0.8.0)
Project-URL: Documentation, https://github.com/twaslowski/py-autowire
Project-URL: Repository, https://github.com/twaslowski/py-autowire
